logurich/__init__.py
logurich/__init__.pyi
logurich/console.py
logurich/core.py
logurich/core.pyi
logurich/handler.py
logurich/opt_click.py
logurich/py.typed
logurich/struct.py
logurich/utils.py
logurich-0.7.1.dist-info/licenses/LICENSE
logurich-0.7.1.dist-info/WHEEL
logurich-0.7.1.dist-info/METADATA
logurich-0.7.1.dist-info/RECORD
