Metadata-Version: 2.4
Name: logurich
Version: 0.7.1
Summary: A Python library combining Loguru and Rich for beautiful logging.
Keywords: logging,loguru,rich,console,terminal,colored-logging,structured-logging,pretty-logging
Author: PakitoSec
Author-email: PakitoSec <jeromep83@gmail.com>
License-Expression: MIT
License-File: LICENSE
Classifier: Development Status :: 4 - Beta
Classifier: Intended Audience :: Developers
Classifier: Topic :: Software Development :: Libraries :: Python Modules
Classifier: Topic :: System :: Logging
Classifier: Programming Language :: Python :: 3
Classifier: Programming Language :: Python :: 3.9
Classifier: Programming Language :: Python :: 3.10
Classifier: Programming Language :: Python :: 3.11
Classifier: Programming Language :: Python :: 3.12
Classifier: Programming Language :: Python :: 3.13
Classifier: Operating System :: OS Independent
Requires-Dist: loguru==0.7.3
Requires-Dist: rich==14.2.0
Requires-Dist: click>=8.1.8 ; extra == 'click'
Requires-Python: >=3.9
Project-URL: Homepage, https://github.com/PakitoSec/logurich
Project-URL: Repository, https://github.com/PakitoSec/logurich
Provides-Extra: click
